phy_cut_paste/__init__.py
phy_cut_paste/simulate.py
phy_cut_paste-0.4.0.dist-info/LICENSE
phy_cut_paste-0.4.0.dist-info/METADATA
phy_cut_paste-0.4.0.dist-info/WHEEL
phy_cut_paste-0.4.0.dist-info/top_level.txt
phy_cut_paste-0.4.0.dist-info/RECORD
