Metadata-Version: 2.1
Name: phy_cut_paste
Version: 0.4.0
Summary: Cut-And-Paste Data Augmentation for Multiple Annotations
Home-page: https://github.com/ainascan/phy_cut_paste
Author: Jack Mead
Author-email: jackmead515@gmail.com
Classifier: Development Status :: 3 - Alpha
Classifier: Intended Audience :: Developers
Classifier: License :: OSI Approved :: MIT License
Classifier: Programming Language :: Python :: 3
Classifier: Programming Language :: Python :: 3.6
Classifier: Programming Language :: Python :: 3.7
Classifier: Programming Language :: Python :: 3.8
License-File: LICENSE
Requires-Dist: pymunk
Requires-Dist: numpy
Requires-Dist: opencv-python
Provides-Extra: dev
Requires-Dist: pygame ; extra == 'dev'
